prog_edu_assistant_tools/__init__.py
prog_edu_assistant_tools/check.py
prog_edu_assistant_tools/magics.py
prog_edu_assistant_tools/magics_test.py
prog_edu_assistant_tools/notebook.py
prog_edu_assistant_tools/summary_test_result.py
prog_edu_assistant_tools-0.3.1.dist-info/LICENSE
prog_edu_assistant_tools-0.3.1.dist-info/METADATA
prog_edu_assistant_tools-0.3.1.dist-info/WHEEL
prog_edu_assistant_tools-0.3.1.dist-info/top_level.txt
prog_edu_assistant_tools-0.3.1.dist-info/RECORD
