Metadata-Version: 2.1
Name: prog-edu-assistant-tools
Version: 0.3.1
Summary: Tools for authoring programming assignments in Jupyter notebooks
Home-page: https://github.com/google/prog-edu-assistant/tree/master/python/prog_edu_assistant_tools
Author: Salikh Zakirov
Author-email: salikh@gmail.com
License: UNKNOWN
Platform: UNKNOWN
Classifier: Programming Language :: Python :: 3
Classifier: License :: OSI Approved :: Apache Software License
Classifier: Operating System :: OS Independent
Requires-Dist: Jinja2
Requires-Dist: IPython
